<mujoco model="model">
  <compiler angle="radian"/>
  <asset>
    <mesh file="visuals/knob_center.obj" name="knob_center_vis"/>
    <mesh file="visuals/knob_front_left.obj" name="knob_front_left_vis"/>
    <mesh file="visuals/knob_front_right.obj" name="knob_front_right_vis"/>
    <mesh file="visuals/knob_rear_left.obj" name="knob_rear_left_vis"/>
    <mesh file="visuals/knob_rear_right.obj" name="knob_rear_right_vis"/>
    <mesh file="visuals/Body001.obj" name="Body001_vis"/>
    <mesh file="visuals/Door001.obj" name="Door001_vis"/>
    <mesh file="visuals/Knob001.obj" name="Knob001_vis"/>
    <mesh file="visuals/Knob002.obj" name="Knob002_vis"/>
    <mesh file="visuals/Shelf001.obj" name="Shelf001_vis"/>
    <texture file="visuals/T_BC001.png" name="Body001_material" type="2d"/>
    <material name="Body001_material" rgba="1 1 1 1.0" texture="Body001_material" shininess="0.4472135901451111" specular="0.3103448502657381"/>
    <texture file="visuals/T_BC001.png" name="knob_center_material" type="2d"/>
    <material name="knob_center_material" rgba="1 1 1 1.0" texture="knob_center_material" shininess="0.4472135901451111" specular="0.3103448502657381"/>
    <texture file="visuals/T_BC001.png" name="knob_front_left_material" type="2d"/>
    <material name="knob_front_left_material" rgba="1 1 1 1.0" texture="knob_front_left_material" shininess="0.4472135901451111" specular="0.3103448502657381"/>
    <texture file="visuals/T_BC001.png" name="knob_front_right_material" type="2d"/>
    <material name="knob_front_right_material" rgba="1 1 1 1.0" texture="knob_front_right_material" shininess="0.4472135901451111" specular="0.3103448502657381"/>
    <texture file="visuals/T_BC001.png" name="knob_rear_left_material" type="2d"/>
    <material name="knob_rear_left_material" rgba="1 1 1 1.0" texture="knob_rear_left_material" shininess="0.4472135901451111" specular="0.3103448502657381"/>
    <texture file="visuals/T_BC001.png" name="knob_rear_right_material" type="2d"/>
    <material name="knob_rear_right_material" rgba="1 1 1 1.0" texture="knob_rear_right_material" shininess="0.4472135901451111" specular="0.3103448502657381"/>
    <texture file="visuals/T_BC001.png" name="Door001_material" type="2d"/>
    <material name="Door001_material" rgba="1 1 1 1.0" texture="Door001_material" shininess="0.4472135901451111" specular="0.3103448502657381"/>
    <texture file="visuals/T_BC001.png" name="Knob001_material" type="2d"/>
    <material name="Knob001_material" rgba="1 1 1 1.0" texture="Knob001_material" shininess="0.4472135901451111" specular="0.3103448502657381"/>
    <texture file="visuals/T_BC001.png" name="Knob002_material" type="2d"/>
    <material name="Knob002_material" rgba="1 1 1 1.0" texture="Knob002_material" shininess="0.4472135901451111" specular="0.3103448502657381"/>
    <texture file="visuals/T_BC001.png" name="Shelf001_material" type="2d"/>
    <material name="Shelf001_material" rgba="1 1 1 1.0" texture="Shelf001_material" shininess="0.4472135901451111" specular="0.3103448502657381"/>
  </asset>
  <default>
    <default class="visual">
      <geom conaffinity="0" contype="0" group="1" type="mesh"/>
    </default>
    <default class="collision">
      <geom group="0" rgba="0.5 0 0 0.5"/>
    </default>
    <default class="spawn">
      <geom group="0" rgba="1 1 1 0.5" contype="0" conaffinity="0"/>
      <site group="0" rgba="1 1 1 0.5"/>
    </default>
    <default class="region">
      <geom group="1" conaffinity="0" contype="0" rgba="0 1 0 0"/>
    </default>
  </default>
  <worldbody>
    <body>
      <body name="object">
        <site type="cylinder" rgba="0 0 0.5 0.5" size="0.049104124307632446 0.010135755874216557" pos="-0.17937184870243073 0.07821726053953171 0.30086642503738403" name="burner_on_rear_left"/>
        <site type="cylinder" rgba="0 0 0.5 0.5" size="0.049104124307632446 0.010135755874216557" pos="0.1781640648841858 0.07821726053953171 0.30086642503738403" name="burner_on_rear_right"/>
        <site type="cylinder" rgba="0 0 0.5 0.5" size="0.049104124307632446 0.010135755874216557" pos="0.1781640648841858 -0.1208408996462822 0.30086642503738403" name="burner_on_front_right"/>
        <site type="cylinder" rgba="0 0 0.5 0.5" size="0.03738318011164665 0.010065660811960697" pos="0.0014598129782825708 -0.022181354463100433 0.301127552986145" name="burner_on_center"/>
        <site type="cylinder" rgba="0 0 0.5 0.5" size="0.049104124307632446 0.010135755874216557" pos="-0.17937184870243073 -0.1208408996462822 0.30086642503738403" name="burner_on_front_left"/>
        <geom mesh="Body001_vis" type="mesh" solimp="0.998 0.998 0.001" solref="0.001 1" density="100" friction="0.95 0.3 0.1" class="visual" material="Body001_material"/>
        <geom class="collision" type="box" pos="-0.0011072009801864624 0.2948773205280304 0.4943579435348511" size="0.03550148010253906 0.38089004158973694 0.09826724976301193" quat="0.7046727538108826 -0.058620162308216095 -0.058620162308216095 -0.7046727538108826"/>
        <geom class="collision" type="box" pos="-0.0011072009801864624 0.303830623626709 -0.0056884437799453735" size="0.3808900713920593 0.03510831668972969 0.5934365391731262" quat="1.0 0.0 0.0 0.0"/>
        <geom class="collision" type="box" pos="-0.0011072529014199972 0.011438732035458088 0.2464621365070343" size="0.38291135430336 0.319195955991745 0.051186900585889816" quat="1.0 0.0 0.0 0.0"/>
        <geom class="collision" type="box" pos="-0.3724724352359772 0.000864348083268851 -0.2022698074579239" size="0.008042119443416595 0.26959511637687683 0.3963606655597687" quat="1.0 0.0 0.0 0.0"/>
        <geom class="collision" type="box" pos="0.3719656467437744 0.0008642111788503826 -0.2022698074579239" size="0.007534710690379143 0.26959502696990967 0.3963605761528015" quat="1.0 0.0 0.0 0.0"/>
        <geom class="collision" type="box" pos="-0.0006107577937655151 -0.0025230133906006813 0.182111456990242" size="0.3794529139995575 0.26609471440315247 0.009091421961784363" quat="1.0 0.0 0.0 0.0"/>
        <geom class="collision" type="box" pos="-0.0006107566878199577 -0.002077348530292511 -0.3584931194782257" size="0.3794529139995575 0.2656489908695221 0.01277067605406046" quat="1.0 0.0 0.0 0.0"/>
        <geom class="collision" type="box" pos="-0.0006107576191425323 -0.02205532416701317 -0.4876742660999298" size="0.3794529139995575 0.28562691807746887 0.11160141229629517" quat="1.0 0.0 0.0 0.0"/>
        <geom class="collision" type="box" pos="-0.0011072009801864624 0.21979333460330963 -0.1270860880613327" size="0.3808900713920593 0.04224236682057381 0.3127388656139374" quat="1.0 0.0 0.0 0.0"/>
        <geom class="collision" type="box" pos="-0.0011072529014199972 0.011802313849329948 -0.49290943145751953" size="0.38291135430336 0.3188323974609375 0.10330064594745636" quat="1.0 0.0 0.0 0.0"/>
        <geom class="collision" type="box" pos="-0.33037519454956055 -0.018898364156484604 0.3101373016834259" size="0.010054855607450008 0.26057958602905273 0.006183778401464224" quat="1.0 0.0 0.0 0.0"/>
        <geom class="collision" type="box" pos="0.0024677887558937073 0.2313532829284668 0.31180259585380554" size="0.3365636169910431 0.010054836980998516 0.0045184846967458725" quat="1.0 0.0 0.0 0.0"/>
        <geom class="collision" type="box" pos="0.0024677885230630636 -0.2680663466453552 0.31008318066596985" size="0.3365636169910431 0.011050592176616192 0.006237924098968506" quat="1.0 0.0 0.0 0.0"/>
        <geom class="collision" type="box" pos="0.002467788988724351 0.18518701195716858 0.31233498454093933" size="0.3365636169910431 0.0055762846022844315 0.00398610346019268" quat="1.0 0.0 0.0 0.0"/>
        <geom class="collision" type="box" pos="-0.28049778938293457 0.13896417617797852 0.31301453709602356" size="0.05359805375337601 0.0055762846022844315 0.0028303328435868025" quat="1.0 0.0 0.0 0.0"/>
        <geom class="collision" type="box" pos="1.8789898604154587e-05 0.1504603922367096 0.31312620639801025" size="0.010665928944945335 0.07293067127466202 0.003194859018549323" quat="1.0 0.0 0.0 0.0"/>
        <geom class="collision" type="box" pos="1.8789898604154587e-05 -0.19198334217071533 0.3128865361213684" size="0.010665928944945335 0.07293067127466202 0.0034345409367233515" quat="1.0 0.0 0.0 0.0"/>
        <geom class="collision" type="box" pos="-0.28049778938293457 0.030646786093711853 0.31349071860313416" size="0.05359805375337601 0.0055762846022844315 0.002830331213772297" quat="1.0 0.0 0.0 0.0"/>
        <geom class="collision" type="box" pos="-0.2744126617908478 0.08292362093925476 0.31280210614204407" size="0.05359805375337601 0.0055762846022844315 0.0028303307481110096" quat="1.0 0.0 0.0 0.0"/>
        <geom class="collision" type="box" pos="-0.2744126617908478 -0.1251562237739563 0.31349071860313416" size="0.05359805375337601 0.0055762846022844315 0.0028303300496190786" quat="1.0 0.0 0.0 0.0"/>
        <geom class="collision" type="box" pos="-0.28049778938293457 -0.17973801493644714 0.31349071860313416" size="0.05359805375337601 0.0055762846022844315 0.0028303295839577913" quat="1.0 0.0 0.0 0.0"/>
        <geom class="collision" type="box" pos="-0.28049778938293457 -0.07219710201025009 0.31349071860313416" size="0.05359805375337601 0.0055762846022844315 0.002830329118296504" quat="1.0 0.0 0.0 0.0"/>
        <geom class="collision" type="box" pos="-0.005766421556472778 -0.22129423916339874 0.31298312544822693" size="0.3283294439315796 0.005841545294970274 0.0033379567321389914" quat="1.0 0.0 0.0 0.0"/>
        <geom class="collision" type="box" pos="0.0014029811136424541 -0.18040184676647186 0.3131220042705536" size="0.13427776098251343 0.0055762846022844315 0.003199032973498106" quat="1.0 0.0 0.0 0.0"/>
        <geom class="collision" type="box" pos="-9.063631296157837e-05 -0.12463986873626709 0.3130607306957245" size="0.13676711916923523 0.0055762846022844315 0.0032603275030851364" quat="1.0 0.0 0.0 0.0"/>
        <geom class="collision" type="box" pos="-0.18092282116413116 -0.21989992260932922 0.31349071860313416" size="0.005576280411332846 0.05359805375337601 0.002830327022820711" quat="1.0 0.0 0.0 0.0"/>
        <geom class="collision" type="box" pos="-0.18092282116413116 -0.020829640328884125 0.3128235936164856" size="0.005576280411332846 0.0605284720659256 0.002830326557159424" quat="1.0 0.0 0.0 0.0"/>
        <geom class="collision" type="box" pos="-0.17067846655845642 -0.021149776875972748 0.3128235936164856" size="0.15144698321819305 0.005576290190219879 0.002830325858667493" quat="1.0 0.0 0.0 0.0"/>
        <geom class="collision" type="box" pos="-0.17953982949256897 0.17737220227718353 0.31301453709602356" size="0.005576279945671558 0.05207677185535431 0.0028303253930062056" quat="1.0 0.0 0.0 0.0"/>
        <geom class="collision" type="box" pos="-0.06138059124350548 -0.016182804480195045 0.31349071860313416" size="0.005576280411332846 0.10434147715568542 0.0028303249273449183" quat="1.0 0.0 0.0 0.0"/>
        <geom class="collision" type="box" pos="0.0007019862532615662 0.08312277495861053 0.31349071860313416" size="0.1360461413860321 0.005576292984187603 0.002830324461683631" quat="1.0 0.0 0.0 0.0"/>
        <geom class="collision" type="box" pos="0.0010117441415786743 0.1365945041179657 0.31349071860313416" size="0.13385549187660217 0.005576292518526316 0.0028303237631917" quat="1.0 0.0 0.0 0.0"/>
        <geom class="collision" type="box" pos="-0.0760592669248581 0.030646786093711853 0.31349071860313416" size="0.056784454733133316 0.005576292518526316 0.0028303232975304127" quat="1.0 0.0 0.0 0.0"/>
        <geom class="collision" type="box" pos="-0.0760592669248581 -0.07211460918188095 0.31290215253829956" size="0.056784454733133316 0.005576292518526316 0.003418905660510063" quat="1.0 0.0 0.0 0.0"/>
        <geom class="collision" type="box" pos="0.07501135766506195 0.031698137521743774 0.31349071860313416" size="0.056784458458423615 0.005576306022703648 0.002830322366207838" quat="1.0 0.0 0.0 0.0"/>
        <geom class="collision" type="box" pos="0.07501135766506195 -0.07191536575555801 0.3128083050251007" size="0.056784458458423615 0.005576306022703648 0.002830321667715907" quat="1.0 0.0 0.0 0.0"/>
        <geom class="collision" type="box" pos="0.16963054239749908 -0.021311767399311066 0.31349071860313416" size="0.15144698321819305 0.005576326511800289 0.00283032120205462" quat="1.0 0.0 0.0 0.0"/>
        <geom class="collision" type="box" pos="0.18131603300571442 -0.020506490021944046 0.31349071860313416" size="0.005576272960752249 0.06144813075661659 0.0028303207363933325" quat="1.0 0.0 0.0 0.0"/>
        <geom class="collision" type="box" pos="0.17987489700317383 0.17948344349861145 0.31349071860313416" size="0.005576273892074823 0.05359805375337601 0.002830320270732045" quat="1.0 0.0 0.0 0.0"/>
        <geom class="collision" type="box" pos="0.2794498801231384 0.031780630350112915 0.31349071860313416" size="0.05359805375337601 0.0055762846022844315 0.002830319572240114" quat="1.0 0.0 0.0 0.0"/>
        <geom class="collision" type="box" pos="0.2794498801231384 0.13932153582572937 0.31349071860313416" size="0.05359805375337601 0.0055762846022844315 0.002830319106578827" quat="1.0 0.0 0.0 0.0"/>
        <geom class="collision" type="box" pos="0.27336472272872925 0.08473974466323853 0.31349071860313416" size="0.05359805375337601 0.0055762846022844315 0.0028303186409175396" quat="1.0 0.0 0.0 0.0"/>
        <geom class="collision" type="box" pos="0.27336472272872925 -0.12467841804027557 0.31349071860313416" size="0.05359805375337601 0.0055762846022844315 0.0028303181752562523" quat="1.0 0.0 0.0 0.0"/>
        <geom class="collision" type="box" pos="0.2794498801231384 -0.07240158319473267 0.31349071860313416" size="0.05359805375337601 0.0055762846022844315 0.0028303174767643213" quat="1.0 0.0 0.0 0.0"/>
        <geom class="collision" type="box" pos="0.2794498801231384 -0.18013902008533478 0.31349071860313416" size="0.05359805375337601 0.0055762846022844315 0.002830317011103034" quat="1.0 0.0 0.0 0.0"/>
        <geom class="collision" type="box" pos="0.3293272852897644 -0.021518105641007423 0.3101373016834259" size="0.010054855607450008 0.26057958602905273 0.0061837416142225266" quat="1.0 0.0 0.0 0.0"/>
        <geom class="collision" type="box" pos="0.061095621436834335 -0.016182804480195045 0.3122764527797699" size="0.005576280411332846 0.10434147715568542 0.0028303160797804594" quat="1.0 0.0 0.0 0.0"/>
        <geom class="collision" type="box" pos="0.1811678111553192 -0.21989992260932922 0.31349071860313416" size="0.005576280411332846 0.05359805375337601 0.0028303153812885284" quat="1.0 0.0 0.0 0.0"/>
        <geom class="collision" type="box" pos="1.8789924070006236e-05 0.0848522037267685 0.2991582155227661" size="0.01066592801362276 0.0060592954978346825 0.012045608833432198" quat="1.0 0.0 0.0 0.0"/>
        <geom class="collision" type="box" pos="-0.05795961245894432 -0.2645678222179413 0.2991582155227661" size="0.0054969703778624535 0.0073637147434055805 0.012045606970787048" quat="1.0 0.0 0.0 0.0"/>
        <geom class="collision" type="box" pos="0.057937826961278915 -0.2645678222179413 0.2991582155227661" size="0.0054969703778624535 0.0073637147434055805 0.012045605108141899" quat="1.0 0.0 0.0 0.0"/>
        <geom class="collision" type="box" pos="0.32452476024627686 -0.18046173453330994 0.2991582155227661" size="0.0054969703778624535 0.0050818296149373055 0.012045602314174175" quat="1.0 0.0 0.0 0.0"/>
        <geom class="collision" type="box" pos="0.32452476024627686 0.14113306999206543 0.2991582155227661" size="0.0054969703778624535 0.0050818296149373055 0.012045600451529026" quat="1.0 0.0 0.0 0.0"/>
        <geom class="collision" type="box" pos="-0.3249405026435852 0.1395174264907837 0.2991582155227661" size="0.0054969703778624535 0.0050818296149373055 0.012045598588883877" quat="1.0 0.0 0.0 0.0"/>
        <geom class="collision" type="box" pos="-0.3249405026435852 -0.18046173453330994 0.2991582155227661" size="0.0054969703778624535 0.0050818296149373055 0.012045596726238728" quat="1.0 0.0 0.0 0.0"/>
        <geom class="collision" type="cylinder" pos="-0.17786848545074463 -0.12142549455165863 0.28634652495384216" size="0.06750943511724472 0.0062187351286411285" quat="1.0 0.0 0.0 0.0"/>
        <geom class="collision" type="cylinder" pos="-0.17911578714847565 -0.12123341113328934 0.29608407616615295" size="0.04891488328576088 0.005066108424216509" quat="1.0 0.0 0.0 0.0"/>
        <geom class="collision" type="cylinder" pos="-0.17911578714847565 -0.12123341113328934 0.30619412660598755" size="0.026130883023142815 0.005198986269533634" quat="1.0 0.0 0.0 0.0"/>
        <geom class="collision" type="cylinder" pos="-0.17911578714847565 0.08057143539190292 0.30619412660598755" size="0.026130883023142815 0.005198986269533634" quat="1.0 0.0 0.0 0.0"/>
        <geom class="collision" type="cylinder" pos="-0.17911578714847565 0.08057143539190292 0.29608407616615295" size="0.04891488328576088 0.005066108424216509" quat="1.0 0.0 0.0 0.0"/>
        <geom class="collision" type="cylinder" pos="-0.17786848545074463 0.08037935197353363 0.28634652495384216" size="0.06750943511724472 0.0062187351286411285" quat="1.0 0.0 0.0 0.0"/>
        <geom class="collision" type="cylinder" pos="0.1783064901828766 0.08037935197353363 0.28634652495384216" size="0.06750943511724472 0.0062187351286411285" quat="1.0 0.0 0.0 0.0"/>
        <geom class="collision" type="cylinder" pos="0.17705918848514557 0.08057143539190292 0.29608407616615295" size="0.04891488328576088 0.005066108424216509" quat="1.0 0.0 0.0 0.0"/>
        <geom class="collision" type="cylinder" pos="0.17705918848514557 0.08057143539190292 0.30619412660598755" size="0.026130883023142815 0.005198986269533634" quat="1.0 0.0 0.0 0.0"/>
        <geom class="collision" type="cylinder" pos="0.17705918848514557 -0.12074483186006546 0.30619412660598755" size="0.026130883023142815 0.005198986269533634" quat="1.0 0.0 0.0 0.0"/>
        <geom class="collision" type="cylinder" pos="0.17705918848514557 -0.12074483186006546 0.29608407616615295" size="0.04891488328576088 0.005066108424216509" quat="1.0 0.0 0.0 0.0"/>
        <geom class="collision" type="cylinder" pos="0.1783064901828766 -0.12093691527843475 0.28634652495384216" size="0.06750943511724472 0.0062187351286411285" quat="1.0 0.0 0.0 0.0"/>
        <geom class="collision" type="cylinder" pos="0.0006507971556857228 -0.02186507359147072 0.29539671540260315" size="0.03809307515621185 0.0054397666826844215" quat="1.0 0.0 0.0 0.0"/>
        <geom class="collision" type="cylinder" pos="0.0007189209572970867 -0.02175668627023697 0.29616522789001465" size="0.020065633580088615 0.00207819533534348" quat="1.0 0.0 0.0 0.0"/>
        <geom class="collision" type="cylinder" pos="0.0008013714104890823 -0.02175668627023697 0.30589744448661804" size="0.01966751553118229 0.005063491407781839" quat="1.0 0.0 0.0 0.0"/>
        <geom class="collision" type="box" pos="0.35568177700042725 -0.05147843062877655 -0.07727119326591492" size="0.009308365173637867 0.2168421894311905 0.0055904989130795" quat="1.0 0.0 0.0 0.0"/>
        <geom class="collision" type="box" pos="-0.35767772793769836 -0.05147843062877655 -0.07727119326591492" size="0.009308365173637867 0.2168421894311905 0.005590497981756926" quat="1.0 0.0 0.0 0.0"/>
        <body name="knob_center">
          <joint axis="0.0 -1.0 0.0" pos="0.11236545443534851 -0.32199516892433167 0.22845515608787537" limited="true" name="knob_center_joint" range="0.0 3.141592653589793" type="hinge" damping="0.05" armature="0.001"/>
          <geom mesh="knob_center_vis" type="mesh" solimp="0.998 0.998 0.001" solref="0.001 1" density="0.01" friction="0.95 0.3 0.1" class="visual" material="knob_center_material"/>
          <geom class="collision" type="cylinder" pos="0.11202821135520935 -0.3141818344593048 0.22797194123268127" size="0.021778227761387825 0.005089934915304184" quat="0.5 0.5 0.4999999701976776 -0.5"/>
          <geom class="collision" type="box" pos="0.11229037493467331 -0.3281225264072418 0.22804969549179077" size="0.008317056111991405 0.008900513872504234 0.021573381498456" quat="1.0 0.0 0.0 0.0"/>
        </body>
        <body name="knob_front_left">
          <joint axis="0.0 -1.0 0.0" pos="-0.10567621141672134 -0.32199516892433167 0.22816339135169983" limited="true" name="knob_front_left_joint" range="0.0 3.141592653589793" type="hinge" damping="0.05" armature="0.001"/>
          <geom mesh="knob_front_left_vis" type="mesh" solimp="0.998 0.998 0.001" solref="0.001 1" density="0.01" friction="0.95 0.3 0.1" class="visual" material="knob_front_left_material"/>
          <geom class="collision" type="cylinder" pos="-0.10575473308563232 -0.3141818344593048 0.22797194123268127" size="0.021778227761387825 0.005089934915304184" quat="0.5 0.5 0.4999999701976776 -0.5"/>
          <geom class="collision" type="box" pos="-0.10549256950616837 -0.3281225264072418 0.22804969549179077" size="0.008317000232636929 0.008900513872504234 0.021573157981038094" quat="1.0 0.0 0.0 0.0"/>
        </body>
        <body name="knob_front_right">
          <joint axis="0.0 -1.0 0.0" pos="0.3330461084842682 -0.32199516892433167 0.22844025492668152" limited="true" name="knob_front_right_joint" range="0.0 3.141592653589793" type="hinge" damping="0.05" armature="0.001"/>
          <geom mesh="knob_front_right_vis" type="mesh" solimp="0.998 0.998 0.001" solref="0.001 1" density="0.01" friction="0.95 0.3 0.1" class="visual" material="knob_front_right_material"/>
          <geom class="collision" type="cylinder" pos="0.3326348662376404 -0.3141818344593048 0.22797194123268127" size="0.021778227761387825 0.005089934915304184" quat="0.5 0.5 0.4999999701976776 -0.5"/>
          <geom class="collision" type="box" pos="0.33289700746536255 -0.3281225264072418 0.22804969549179077" size="0.00831705704331398 0.008900513872504234 0.0215733852237463" quat="1.0 0.0 0.0 0.0"/>
        </body>
        <body name="knob_rear_left">
          <joint axis="0.0 -1.0 0.0" pos="0.0019745733588933945 -0.32199516892433167 0.22816339135169983" limited="true" name="knob_rear_left_joint" range="0.0 3.141592653589793" type="hinge" damping="0.05" armature="0.001"/>
          <geom mesh="knob_rear_left_vis" type="mesh" solimp="0.998 0.998 0.001" solref="0.001 1" density="0.01" friction="0.95 0.3 0.1" class="visual" material="knob_rear_left_material"/>
          <geom class="collision" type="cylinder" pos="0.0017683517653495073 -0.3141818344593048 0.22797194123268127" size="0.021778227761387825 0.005089934915304184" quat="0.5 0.5 0.4999999701976776 -0.5"/>
          <geom class="collision" type="box" pos="0.002030515344813466 -0.3281225264072418 0.22804969549179077" size="0.008317057974636555 0.008900513872504234 0.021573388949036598" quat="1.0 0.0 0.0 0.0"/>
        </body>
        <body name="knob_rear_right">
          <joint axis="0.0 -1.0 0.0" pos="0.2226048707962036 -0.32199516892433167 0.22874930500984192" limited="true" name="knob_rear_right_joint" range="0.0 3.141592653589793" type="hinge" damping="0.05" armature="0.001"/>
          <geom mesh="knob_rear_right_vis" type="mesh" solimp="0.998 0.998 0.001" solref="0.001 1" density="0.01" friction="0.95 0.3 0.1" class="visual" material="knob_rear_right_material"/>
          <geom class="collision" type="cylinder" pos="0.222537100315094 -0.3141818344593048 0.22823043167591095" size="0.021778227761387825 0.005089934915304184" quat="0.5 0.5 0.4999999701976776 -0.5"/>
          <geom class="collision" type="box" pos="0.22279925644397736 -0.3281225264072418 0.22830818593502045" size="0.008317059837281704 0.008900513872504234 0.021573392674326897" quat="1.0 0.0 0.0 0.0"/>
        </body>
        <body name="Door001">
          <joint axis="1.0 0.0 0.0" pos="-8.847564458847046e-09 -0.30366650223731995 -0.36699461936950684" limited="true" name="Door001_joint" range="0.0 1.5707963267948966" type="hinge" damping="1" frictionloss="1" armature=".01" stiffness="0.05"/>
          <geom mesh="Door001_vis" type="mesh" solimp="0.998 0.998 0.001" solref="0.001 1" density="100" friction="0.95 0.3 0.1" class="visual" material="Door001_material"/>
          <geom class="collision" type="box" pos="-0.0006107241497375071 -0.2897120416164398 -0.09184369444847107" size="0.3794528543949127 0.016666023060679436 0.2750031352043152" quat="1.0 0.0 0.0 0.0"/>
          <geom class="collision" type="box" pos="-0.3148968517780304 -0.3060145676136017 0.1599554866552353" size="0.022222835570573807 0.0024574706330895424 0.019035546109080315" quat="1.0 0.0 0.0 0.0"/>
          <geom class="collision" type="box" pos="-0.2709410488605499 -0.3097946047782898 0.15919506549835205" size="0.0024574636481702328 0.022222571074962616 0.0205561351031065" quat="0.6362748742103577 0.0 0.0 -0.7714624404907227"/>
          <geom class="collision" type="box" pos="-0.227435901761055 -0.31843802332878113 0.15919506549835205" size="0.0024574636481702328 0.022222571074962616 0.0205561351031065" quat="0.6362748742103577 0.0 0.0 -0.7714624404907227"/>
          <geom class="collision" type="box" pos="-0.1837867647409439 -0.3264331817626953 0.15919506549835205" size="0.0024574636481702328 0.022222576662898064 0.0205561351031065" quat="0.6439476609230042 0.0 0.0 -0.7650695443153381"/>
          <geom class="collision" type="box" pos="-0.13977740705013275 -0.3331318795681 0.15919506549835205" size="0.0024574636481702328 0.022222567349672318 0.0205561351031065" quat="0.6602786183357239 0.0 0.0 -0.7510207295417786"/>
          <geom class="collision" type="box" pos="-0.09540002048015594 -0.3381817638874054 0.15919506549835205" size="0.0024574636481702328 0.022222572937607765 0.0205561351031065" quat="0.678578794002533 0.0 0.0 -0.7345276474952698"/>
          <geom class="collision" type="box" pos="-0.05112968757748604 -0.34129592776298523 0.15919506549835205" size="0.0024574636481702328 0.022222572937607765 0.0205561351031065" quat="0.6858806014060974 0.0 0.0 -0.7277140617370605"/>
          <geom class="collision" type="box" pos="-0.006646857131272554 -0.3430190980434418 0.15919506549835205" size="0.0024574636481702328 0.022222572937607765 0.0205561351031065" quat="0.7013971209526062 0.0 0.0 -0.7127707004547119"/>
          <geom class="collision" type="box" pos="0.037287160754203796 -0.3420933783054352 0.15919506549835205" size="0.022292759269475937 0.0032048795837908983 0.0205561351031065" quat="1.0 0.0 0.0 0.0"/>
          <geom class="collision" type="box" pos="0.08173812925815582 -0.33968374133110046 0.15919509530067444" size="0.0024574636481702328 0.022222574800252914 0.0205561351031065" quat="0.7337282299995422 0.0 0.0 -0.6794430613517761"/>
          <geom class="collision" type="box" pos="0.1260979324579239 -0.33503004908561707 0.15919506549835205" size="0.0024574636481702328 0.022222571074962616 0.0205561351031065" quat="0.7502427101135254 0.0 0.0 -0.6611624956130981"/>
          <geom class="collision" type="box" pos="0.17006130516529083 -0.3289969265460968 0.15919509530067444" size="0.0024574636481702328 0.022222578525543213 0.0205561351031065" quat="0.7568084001541138 0.0 0.0 -0.6536368131637573"/>
          <geom class="collision" type="box" pos="0.21386194229125977 -0.32126954197883606 0.15919509530067444" size="0.0024574636481702328 0.022222574800252914 0.0205561351031065" quat="0.7731620073318481 0.0 0.0 -0.6342085599899292"/>
          <geom class="collision" type="box" pos="0.25716546177864075 -0.3125396966934204 0.15919509530067444" size="0.0024574636481702328 0.022222574800252914 0.0205561351031065" quat="0.7731620073318481 0.0 0.0 -0.6342085599899292"/>
          <geom class="collision" type="box" pos="0.3008146584033966 -0.3046742081642151 0.15919506549835205" size="0.0024574636481702328 0.022222571074962616 0.0205561351031065" quat="0.7578297257423401 0.0 0.0 -0.6524524092674255"/>
          <geom class="collision" type="box" pos="0.3170888125896454 -0.30482158064842224 0.1599554866552353" size="0.022301524877548218 0.0033225626684725285 0.01903529278934002" quat="1.0 0.0 0.0 0.0"/>
        </body>
        <body name="Knob001">
          <joint axis="0.0 1.0 0.0" pos="-0.3297596275806427 -0.32199516892433167 0.22616426646709442" limited="true" name="Knob001_joint" range="0.0 4.363323129985823" type="hinge" damping="0.05" armature="0.001"/>
          <geom mesh="Knob001_vis" type="mesh" solimp="0.998 0.998 0.001" solref="0.001 1" density="0.01" friction="0.95 0.3 0.1" class="visual" material="Knob001_material"/>
          <geom class="collision" type="cylinder" pos="-0.3298175632953644 -0.3142632842063904 0.22624410688877106" size="0.017223043367266655 0.004585263319313526" quat="0.21008676290512085 0.21008668839931488 0.675176739692688 -0.6751766800880432"/>
          <geom class="collision" type="box" pos="-0.3298751413822174 -0.3279712200164795 0.22614088654518127" size="0.009020081721246243 0.006863096263259649 0.01700630784034729" quat="0.6268594861030579 -0.3271808922290802 0.32718098163604736 -0.626859188079834"/>
        </body>
        <body name="Knob002">
          <joint axis="0.0 1.0 0.0" pos="-0.21431708335876465 -0.3215131163597107 0.224481999874115" limited="true" name="Knob002_joint" range="0.0 4.014257279586958" type="hinge" damping="0.05" armature="0.001"/>
          <geom mesh="Knob002_vis" type="mesh" solimp="0.998 0.998 0.001" solref="0.001 1" density="0.01" friction="0.95 0.3 0.1" class="visual" material="Knob002_material"/>
          <geom class="collision" type="cylinder" pos="-0.21431055665016174 -0.31357234716415405 0.22450335323810577" size="0.019157784059643745 0.005100345704704523" quat="0.5018826723098755 0.5018810033798218 -0.4981120228767395 0.4981100559234619"/>
          <geom class="collision" type="box" pos="-0.21436703205108643 -0.3285992741584778 0.2249629646539688" size="0.0075588831678032875 0.009881828911602497 0.018647171556949615" quat="1.0 0.0 0.0 0.0"/>
        </body>
        <body name="Shelf001">
          <joint axis="0.0 -1.0 0.0" pos="-0.0014170813374221325 -0.050423361361026764 -0.06651343405246735" limited="true" name="Shelf001_joint" range="0.0 0.4" type="slide" damping="1" frictionloss="1" armature=".01" stiffness="0.05"/>
          <geom mesh="Shelf001_vis" type="mesh" solimp="0.998 0.998 0.001" solref="0.001 1" density="100" friction="0.95 0.3 0.1" class="visual" material="Shelf001_material"/>
          <geom class="collision" type="box" pos="-0.001009155297651887 -0.0503695011138916 -0.06649315357208252" size="0.35340452194213867 0.20836016535758972 0.004014915321022272" quat="1.0 0.0 0.0 0.0"/>
        </body>
        <geom class="region" name="reg_main" type="box" pos="0.0 0.011378571391105652 -0.16445110738277435" size="0.37950003147125244 0.31861060857772827 0.4299965500831604"/>
        <geom class="region" name="reg_int" type="box" pos="0.0020640790462493896 -0.04484175145626068 -0.07618213444948196" size="0.35594722628593445 0.22476963698863983 0.2550886198878288"/>
      </body>
    </body>
  </worldbody>
  <actuator>
    <motor name="knob_center_joint_actuator" joint="knob_center_joint" gear="10"/>
    <motor name="knob_front_left_joint_actuator" joint="knob_front_left_joint" gear="10"/>
    <motor name="knob_front_right_joint_actuator" joint="knob_front_right_joint" gear="10"/>
    <motor name="knob_rear_left_joint_actuator" joint="knob_rear_left_joint" gear="10"/>
    <motor name="knob_rear_right_joint_actuator" joint="knob_rear_right_joint" gear="10"/>
    <motor name="Door001_joint_actuator" joint="Door001_joint" gear="50"/>
    <motor name="Knob001_joint_actuator" joint="Knob001_joint" gear="50"/>
    <motor name="Knob002_joint_actuator" joint="Knob002_joint" gear="50"/>
    <motor name="Shelf001_joint_actuator" joint="Shelf001_joint" gear="50"/>
  </actuator>
</mujoco>
